nicegui_extras/__init__.py
nicegui_extras/styles.py
nicegui_extras/themes.py
nicegui_extras/utils.py
nicegui_extras-0.2.dist-info/METADATA
nicegui_extras-0.2.dist-info/WHEEL
nicegui_extras-0.2.dist-info/top_level.txt
nicegui_extras-0.2.dist-info/RECORD
