Metadata-Version: 2.4
Name: nicegui-extras
Version: 0.2
Summary: A collection of CSS and utility helpers for NiceGUI
Author-email: Ali Heydari <imrrobat@gmail.com>
License: MIT
Project-URL: Homepage, https://github.com/imrrobat/nicegui-extras
Requires-Dist: nicegui>=1.4.0
